httmcp/__init__.py
httmcp/__main__.py
httmcp/core.py
httmcp-0.3.1.dist-info/METADATA
httmcp-0.3.1.dist-info/WHEEL
httmcp-0.3.1.dist-info/entry_points.txt
httmcp-0.3.1.dist-info/top_level.txt
httmcp-0.3.1.dist-info/RECORD
