Metadata-Version: 2.4
Name: httmcp
Version: 0.3.1
Summary: HTTP MCP Transport for Nchan
Home-page: https://github.com/conechoai/nchan-mcp-transport
Author: lloydzhou
Author-email: lloydzhou@qq.com
Classifier: Programming Language :: Python :: 3
Classifier: License :: OSI Approved :: MIT License
Classifier: Operating System :: OS Independent
Classifier: Development Status :: 4 - Beta
Classifier: Intended Audience :: Developers
Classifier: Topic :: Software Development :: Libraries :: Python Modules
Requires-Python: >=3.10
Requires-Dist: fastapi>=0.115.11
Requires-Dist: httpx>=0.27.0
Requires-Dist: openapi-httpx-client>=0.4.1
Requires-Dist: mcp>=1.3.0
Provides-Extra: cli
Requires-Dist: uvicorn>=0.22.0; extra == "cli"
Requires-Dist: argparse>=1.4.0; extra == "cli"
Dynamic: author
Dynamic: author-email
Dynamic: classifier
Dynamic: description
Dynamic: description-content-type
Dynamic: home-page
Dynamic: provides-extra
Dynamic: requires-dist
Dynamic: requires-python
Dynamic: summary
